lumify/__init__.py
lumify-1.0.0.dist-info/METADATA
lumify-1.0.0.dist-info/WHEEL
lumify-1.0.0.dist-info/top_level.txt
lumify-1.0.0.dist-info/RECORD
