Metadata-Version: 2.1
Name: lumify
Version: 1.0.0
Summary: lumify
Author: Malix
Author-email: malixfloof@gmail.com
Classifier: Programming Language :: Python :: 3
Classifier: License :: OSI Approved :: MIT License
Classifier: Operating System :: OS Independent
Requires-Python: >=3.11
